dataflow/__init__.py
dataflow/dataflow.py
dataflow/state.py
pydataflow-0.0.5.dist-info/LICENSE
pydataflow-0.0.5.dist-info/METADATA
pydataflow-0.0.5.dist-info/WHEEL
pydataflow-0.0.5.dist-info/top_level.txt
pydataflow-0.0.5.dist-info/RECORD
