Metadata-Version: 2.1
Name: pydataflow
Version: 0.0.5
Summary: a simple dataflow / workflow engine
Home-page: https://github.com/kr-g/pydataflow
Author: k.r. goger
Author-email: k.r.goger+pydataflow@gmail.com
License: MIT
Keywords: utility framework dataflow workflow automation
Platform: UNKNOWN
Classifier: Development Status :: 3 - Alpha
Classifier: Operating System :: POSIX :: Linux
Classifier: Intended Audience :: Developers
Classifier: Topic :: Utilities
Classifier: Programming Language :: Python :: 3
Classifier: License :: OSI Approved :: GNU Affero General Public License v3 or later (AGPLv3+)
Requires-Python: >=3.6
License-File: LICENSE
